OpenstfLibrary/VERSION
OpenstfLibrary/__init__.py
OpenstfLibrary/http.py
robotframework_openstflibrary-0.1.1.dist-info/DESCRIPTION.rst
robotframework_openstflibrary-0.1.1.dist-info/METADATA
robotframework_openstflibrary-0.1.1.dist-info/RECORD
robotframework_openstflibrary-0.1.1.dist-info/WHEEL
robotframework_openstflibrary-0.1.1.dist-info/metadata.json
robotframework_openstflibrary-0.1.1.dist-info/top_level.txt
