Metadata-Version: 2.0
Name: robotframework-openstflibrary
Version: 0.1.1
Summary: Openstf utility library for Robot Framework
Home-page: https://github.com/ravihuang/Robotframework-OpenstfLibrary
Author: Ravi Huang
Author-email: ravi.huang@gmail.com
License: Apache License 2.0
Keywords: robotframework testing testautomation openstf android
Platform: any
Classifier: Development Status :: 2 - Pre-Alpha
Classifier: License :: OSI Approved :: Apache Software License
Classifier: Operating System :: OS Independent
Classifier: Programming Language :: Python
Classifier: Programming Language :: Python :: 2
Classifier: Programming Language :: Python :: 3
Classifier: Topic :: Software Development :: Testing
Classifier: Framework :: Robot Framework
Classifier: Framework :: Robot Framework :: Library
Requires-Dist: robotframework
Requires-Dist: pyswagger
